{
    "Material": "Graphite/Epoxy",
    "Property": "Compression Strength",
    "Test Environment": "ETW",
    "Program": "Qualification Data",
    "batches": {
        "1": {
            "datasets": {
                "1": {
                    "coupons": {
                        "1": 106.358,
                        "2": 105.899,
                        "3": 88.464,
                        "4": 103.902,
                        "5": 80.206,
                        "6": 109.2,
                        "7": 61.014
                    }
                }
            }
        },
        "2": {
            "datasets": {
                "2": {
                    "coupons": {
                        "1": 99.321,
                        "2": 115.862,
                        "3": 82.613,
                        "4": 85.369,
                        "5": 115.802,
                        "6": 44.322,
                        "7": 117.328,
                        "8": 88.678
                    }
                }
            }
        },
        "3": {
            "datasets": {
                "3": {
                    "coupons": {
                        "1": 107.677,
                        "2": 108.960,
                        "3": 116.123,
                        "4": 80.233,
                        "5": 106.146,
                        "6": 104.668,
                        "7": 104.235
                    }
                }
            }
        }
    }
}